simple_nexus_dashboard/__init__.py
simple_nexus_dashboard/rest_client/LICENSE
simple_nexus_dashboard/rest_client/README
simple_nexus_dashboard/rest_client/__init__.py
simple_nexus_dashboard/rest_client/api.py
simple_nexus_dashboard/rest_client/curlify.py
simple_nexus_dashboard/rest_client/decorators.py
simple_nexus_dashboard/rest_client/exceptions.py
simple_nexus_dashboard/rest_client/models.py
simple_nexus_dashboard/rest_client/request.py
simple_nexus_dashboard/rest_client/resource.py
simple_nexus_dashboard-0.1.dist-info/LICENSE
simple_nexus_dashboard-0.1.dist-info/METADATA
simple_nexus_dashboard-0.1.dist-info/WHEEL
simple_nexus_dashboard-0.1.dist-info/top_level.txt
simple_nexus_dashboard-0.1.dist-info/RECORD
