Metadata-Version: 2.1
Name: simple-nexus-dashboard
Version: 0.1
Summary: Simple REST-client for Cisco Nexus Dashboard
Home-page: https://github.com/jinjamator/simple_nexus_dashboard
Author: Wilhelm Putz
Author-email: wilhelm.putz@cancom.com
License: ASL V2
Platform: UNKNOWN
Classifier: License :: OSI Approved :: Apache Software License
Classifier: Programming Language :: Python :: 3.10
Classifier: Programming Language :: Python :: 3.11
Classifier: Programming Language :: Python :: 3.12
Classifier: Programming Language :: Python :: 3.13
Classifier: Topic :: System :: Installation/Setup
Classifier: Topic :: System :: Systems Administration
Classifier: Topic :: Utilities
Requires-Python: >=3.7
License-File: LICENSE
Requires-Dist: httpx
